rstwatch/__init__.py
rstwatch/__main__.py
rstwatch/api.py
rstwatch/util.py
rstwatch/version.py
rstwatch-1.0.3.dist-info/LICENSE.txt
rstwatch-1.0.3.dist-info/METADATA
rstwatch-1.0.3.dist-info/WHEEL
rstwatch-1.0.3.dist-info/entry_points.txt
rstwatch-1.0.3.dist-info/top_level.txt
rstwatch-1.0.3.dist-info/RECORD
