Metadata-Version: 2.1
Name: rstwatch
Version: 1.0.3
Summary: Watch directories for changes to RST files and generate HTML
Home-page: https://bitbucket.org/dhandy2013/rstwatch
Author: David Handy
Author-email: cpif@handysoftware.com
License: BSD-2-Clause
Download-URL: https://bitbucket.org/dhandy2013/rstwatch/get/tip.zip
Platform: UNKNOWN
Classifier: Environment :: Console
Classifier: License :: OSI Approved :: BSD License
Classifier: Operating System :: MacOS :: MacOS X
Classifier: Operating System :: POSIX :: Linux
Classifier: Operating System :: Microsoft :: Windows :: Windows 7
Classifier: Operating System :: Microsoft :: Windows :: Windows 10
Classifier: Programming Language :: Python :: 2
Classifier: Programming Language :: Python :: 2.7
Classifier: Programming Language :: Python :: 3
Classifier: Programming Language :: Python :: 3.5
Classifier: Programming Language :: Python :: 3.6
Classifier: Programming Language :: Python :: 3.7
Classifier: Topic :: Documentation
Classifier: Topic :: Text Processing :: Markup :: HTML
Requires-Dist: docopt (>=0.5.0)
Requires-Dist: docutils (>=0.13)
